fintextract/__init__.py
fintextract/main.py
fintextract/prompts.py
fintextract-2025.12.21122420.dist-info/METADATA
fintextract-2025.12.21122420.dist-info/WHEEL
fintextract-2025.12.21122420.dist-info/top_level.txt
fintextract-2025.12.21122420.dist-info/RECORD
