Metadata-Version: 2.4
Name: fintextract
Version: 2025.12.21122420
Summary: A new package designed to extract and structure key financial and business insights from unstructured news text. The package takes raw news text as input and returns a structured summary containing th
Author-email: fintextract <hi@eugene.plus>
License: MIT
Project-URL: Homepage, https://github.com/chigwell/fintextract
Requires-Python: >=3.9
Requires-Dist: langchain-llm7>=0.0.0
Requires-Dist: llmatch-messages>=0.0.0
Requires-Dist: langchain-core>=0.3.0
